bomradarloop/__init__.py
bomradarloop-0.2.0.dist-info/LICENSE
bomradarloop-0.2.0.dist-info/METADATA
bomradarloop-0.2.0.dist-info/WHEEL
bomradarloop-0.2.0.dist-info/top_level.txt
bomradarloop-0.2.0.dist-info/RECORD
